<document xml:lang="sms" id="no_id">
  <header>
    <title>Sääʹmteʹǧǧ oudd teâttân, što ooccamnalla lij mieʹrräiggaž aaʹššI ouʹddepuʹhtti</title>
    <genre code="admin"/>
    <author>
      <unknown/>
    </author>
    <translator>
      <unknown/>
    </translator>
    <translated_from xml:lang="fin"/>
    <year>2015</year>
    <wordcount>135</wordcount>
    <conversion_status type="standard"/>
    <availability>
      <free/>
    </availability>
    <multilingual/>
    <origFileName>http://www.samediggi.fi/index.php?option=com_docman&amp;task=doc_download&amp;gid=2583&amp;Itemid=10</origFileName>
    <parallel_text xml:lang="fin" location="ilm_sotesiht2015.pdf"/>
    <parallel_text xml:lang="sme" location="ilm_sotesiht2015.pdf"/>
    <parallel_text xml:lang="smn" location="ilm_sotesiht2015.pdf"/>
    <metadata>
      <uncomplete/>
    </metadata>
    <version>XSLtemplate $Revision: 125457 $; file-specific xsl  Revision; common.xsl  $Revision: 154948 $; </version>
  </header>
  <body>
    <p>Sääʹmteʹǧǧ oudd teâttân, što ooccamnalla lij</p>
    <p xml:lang="deu">    MIEʹRRÄIGGAŽ AAʹŠŠI OUʹDDEPUʹHTTI  </p>
    <p>tuâjj. Aaʹšši ouʹddepuʹhtti ouddtuâjjan lij tuåimmjed sosiaal- da tiõrvâsvuõttluʹvddkååʹdd aaʹšši ouʹddepuʹhttjen da piisren. Tuâjj älgg mââʹjeeǩâni da poott 19.6.2015. Tuâjjla tuåimpäiʹǩǩ lij tuâjjlažkååʹdd ouddtuåimpääiʹǩest sääʹmkulttuurkõõskõõzz  Sajoozzâst,  Aanrest.  Šiõttõsvuâđđliʹžžân  lij  veeʹrj  ooudldem  škoouʹlʼjumuš  da lââʹssen  õõlǥtet  sääʹmǩiõl  silttõõzz  (asetõs  1727/95).  Tuâi  oʹnnstemvuõđlaž  håiddmõõžž  ooudad  ââʹnteei õllškooultuʹtǩǩõs,  šiõǥǥ    sääʹm  sosiaal-,  tiõrvâsvuõđ-  da  vuõsspeâmmamämmatvuuʹđ  tobddmõš.  Šiõǥǥ vaaldšemvuõđlaž  tuâjai  da  täällvaaldšem  tobddmõš  ǩiõččât  ouddõssân.  Päʹlǩǩmõš  meäʹrrââtt  sääʹmteeʹǧǧ päʹlǩǩmõšriâšldõõǥǥ õõlǥtemtääʹzz IV/IV-II mieʹldd (vuâđđpäʹlǩǩ lij välillä 2 457,04 – 2 560,57 eeuʹr kõõskâst määʹnnpââʹj).  Vuâđđpääʹlǩ  lââʹssen  määuʹset  24  %:n  sääʹmvuuʹd  lââʹzz  da  tuâjjtobddâmlââʹzz  mieʹldd meäʹrrõõtti  tuâjjtobddâm  lääʹzz.    .  Ooccmõõžž  mieʹlddõõzzineez  âʼʹlǧǧe  tuåimtet  sääʹmteeʹǧǧ  tuâjjlažkådda 27.2.2015  čiâss    16.00  mõõʹneeʹst  addrõõzzin  Sajos,  99870  Aanar.  Lââʹssteâđaid  tuâjast  oudd  mä. vaaldšemjååʹđteei  Pia  Ruotsala  teʹl.  010  839  3106.  Sääʹmteeʹǧǧ  tuåimjumuʹšše  vuäitt  tobddstõõttâd neʹttaddrõõzzâst www.samediggi.fi</p>
    <p>Aanrest 12.2.2015    Sääʹmteʹǧǧ</p>
  </body>
</document>
