<document xml:lang="sms" id="no_id">
  <header>
    <title>Sää ́mte ́ǧǧvaal 2007</title>
    <genre code="admin"/>
    <author>
      <unknown/>
    </author>
    <year>2007</year>
    <wordcount>120</wordcount>
    <conversion_status type="standard"/>
    <availability>
      <free/>
    </availability>
    <multilingual/>
    <origFileName>http://www.samediggi.fi/index.php?option=com_docman&amp;task=doc_download&amp;gid=53&amp;Itemid=10</origFileName>
    <parallel_text location="samedikki_valggat_2007_samitige_vaaljah_2007_saamelaiskarajien_vaalit_2007.pdf" xml:lang="smn"/>
    <parallel_text location="samedikki_valggat_2007_samitige_vaaljah_2007_saamelaiskarajien_vaalit_2007.pdf" xml:lang="sme"/>
    <parallel_text location="samedikki_valggat_2007_samitige_vaaljah_2007_saamelaiskarajien_vaalit_2007.pdf" xml:lang="fin"/>
    <metadata>
      <uncomplete/>
    </metadata>
    <version>XSLtemplate $Revision: 139793 $; file-specific xsl  Revision; common.xsl  $Revision: 134027 $; </version>
  </header>
  <body>
    <p>SääŠmteŠĐĐvaal 2007 SääŠmteŠĐĐvaal ââŠnet 3.9. - 1.10.2007 kõõskâst. Vaal-lo•stõk lij vueiŠnnemnalla pâŠzzlâšttam-mannu 15. - 28. peeiŠvi kõõskâst „iâss 10.00 - 14.00 täin paaiŠ³in:</p>
    <p>SääŠmteeŠĐĐ koontâr  Hetta, Tunturi-Lapin luontokeskus, Peuratie 15  SääŠmteeŠĐĐ koontâr  Aanar, Saarikoskentie 4 SääŠmteeŠĐĐ koontâr  Uccjokk, KåŠddveŠrĐĐpõrtt Vuõccu škooul  Vuõccu, Ivalontie 8716</p>
    <p>JuõŠ³³kaø vuäitt še taŠr³³eed jiiŠjjes kuõskki vaal-lo•stõŠ³³e mieŠr³³uum teâ˜ vuõiŠĐĐest vaalluŠvddkååŠdd konttrest teŠlf. (016) 665 038, (016) 665 027, 050493 9018, fakss (016) 671 323 leŠbe</p>
    <p>vaalit@samediggi.fi leŠbe jieŠleeŠl kiõ„„men vaal-lo•stõõ••âst pââibeäŠlnn sarnnum pääiŠ³in</p>
    <p>äävaiåårramääiŠjest.</p>
    <p>KååŠtt ³eä„„, što suu leät kuâ˜˜am vuõiggâdvuõ˜tää meädda vaal-lo•stõõ••âst leŠbe što suu kuõskki mieŠr³³õs vaal-lo•stõõ••âst lij puästtad, vuäitt raukkâd vuõi•õõzz ³eeŠrjteeŠl vaal-luŠvddkådda mââimõõzzâst njuh„„mannu 11. peeiŠv ouddâl „iâss 16.00. Vuõi•eem-mõõntõõllâmvuäŠppõõzz vuäˆˆ vaal-luŠvddkååŠdd konttrest leŠbe tõid vuäitt kuõrrâd www.samediggi.fi.</p>
    <p>Aanrest 28.2.2007 Vaal-luŠvddkåŠdd</p>
  </body>
</document>
