<document xml:lang="sms" id="no_id"><header><title>Samediggi - Saamelaiskäräjät - Sää&amp;#697;mtee&amp;#697;&amp;#487;&amp;#487; sååbbar</title><genre code="admin"/><author><unknown/></author><translator><unknown/></translator><translated_from xml:lang="fin"/><wordcount>129</wordcount><conversion_status type="standard"/><availability><free/></availability><submitter name="Børre Gaup" email="albbas@gmail.com"/><multilingual><language xml:lang="fin"/></multilingual><origFileName>http://www.samediggi.fi/index2.php?option=com_content&amp;task=view&amp;id=6&amp;lang=nuortta.html</origFileName><parallel_text xml:lang="eng" location="index2.php_option=com_content_task=view_id=6_lang=english.html"/><parallel_text xml:lang="fin" location="index2.php_option=com_content_task=view_id=6_lang=finnish.html"/><parallel_text xml:lang="sme" location="index2.php_option=com_content_task=view_id=6_lang=davvi.html"/><parallel_text xml:lang="smn" location="index2.php_option=com_content_task=view_id=6_lang=anaras.html"/><metadata><uncomplete/></metadata><version>XSLtemplate $Revision$; file-specific xsl  Revision; common.xsl  $Revision: 154948 $; </version></header><body><p>Sääʹmteeʹǧǧ sååbbar</p>
<p>Sääʹmteeʹǧǧ sååbbar eeʹttkâʹstt Sääʹmteeʹǧǧ pââimõs tuʹmmjemvääʹld. Tõt noorââtt 4-5 vuâra eeʹjjest. Sääʹmteeʹǧǧ sååbbar tuʹmmai jäänmõsân nåkam ceâlklmõõžžin, čuäʹjtõõzzin da jeeʹres beäʹlestväʹlddmõõžžid, koid sääʹmteʹǧǧ lij ouddam. Valdiasååbbar mieʹrrad sääʹmteeʹǧǧ vuässliʹžžen (21) da vääʹrrvuässliʹžžen (4) sääʹmteeʹǧǧ vaalin jäänmõsân jiõnid vuäǯǯam oummid, seârvvna nuʹtt, što juõʹǩǩ sääʹm dommvuuʹd kååʹddest (Enontekiö, Aanar, Suäʹđjel da Uccjokk) âlgg leeʹd uuʹccmõsân kolmm vuässla da pukin täin kooʹddin õhtt vääʹrrvuässlaž.</p>
<p>Tuåimmpââi 2012 - 2015 vuässla da vääʹrrvuässla:</p>
<p><em type="italic">Vuässla: </em> </p>
<p xml:lang="fin">Sanila-Aikio Tiina, sj.</p>
<p>Paltto Heikki, I vääʹrrsj.</p>
<p>Magga Ulla-Maarit, II vääʹrrsj.</p>
<p>Avaskari Anu</p>
<p>Guttorm Veikko</p>
<p xml:lang="fin">Haltta Tauno</p>
<p xml:lang="fin">Heikkuri Pertti</p>
<p xml:lang="fin">Hetta Jouko</p>
<p xml:lang="fin">Länsman Asko</p>
<p>Magga-Vars Petra</p>
<p xml:lang="fin">Morottaja Anna</p>
<p xml:lang="fin">Musta Yrjö</p>
<p>Nuorgam Anne</p>
<p xml:lang="fin">Näkkäläjärvi Janne</p>
<p xml:lang="fin">Pohjanrinne Arto</p>
<p>Porsanger Veikko</p>
<p xml:lang="fin">Tapiola Ilmari</p>
<p xml:lang="fin">Tapiola Nilla</p>
<p xml:lang="fin">Valkeapää Nihkolas</p>
<p xml:lang="fin">Valle Pentti</p>
<p xml:lang="fin">Äärelä Rauni</p>
<p><em type="italic">Vääʹrrvuässla: </em> </p>
<p xml:lang="fin">Aikio Antti</p>
<p xml:lang="fin">Juuso Tuomas Aslak</p>
<p xml:lang="fin">Pekkala Pekka</p>
<p xml:lang="fin">Sujala Antti</p>
</body></document>