<document xml:lang="sms" id="no_id"><header><title>Mieʹrräiggsa projeʹktt-tuâjjla Sääʹm-musikk-kõõskõʹšše - Samediggi</title><genre code="admin"/><author><unknown/></author><translator><unknown/></translator><translated_from xml:lang="fin"/><year>2018</year><wordcount>108</wordcount><conversion_status type="standard"/><availability><free/></availability><multilingual/><origFileName>https://www.samediggi.fi/2018/04/18/mierraiggsa-projektt-tuajjla-saam-musikk-kooskosse/?lang=nuo</origFileName><parallel_text xml:lang="fin" location="maaraaikainen_projektityontekija_saamelaismusiikkikeskukselle.html"/><parallel_text xml:lang="sme" location="mearreaigasas_proseaktabargi_samemusihkkaguovddazii.html"/><parallel_text xml:lang="smn" location="meriaigasii_proojeektpargee_saami_muusikkuavdazan.html"/><metadata><uncomplete/></metadata><version>XSLtemplate $Revision$; file-specific xsl  Revision; common.xsl  $Revision$; </version></header><body><p type="title">Mieʹrräiggsa projeʹktt-tuâjjla Sääʹm-musikk-kõõskõʹšše</p>
<p>Tuâjj älgg 4.6 da peštt 31.8.2018 räjja. Projeʹktt-tuâjjla tuõjju kooll jm. sääʹm-musikk-kõõskõõzz veäʹǩǩteeʹjen tuåimmjumuš di Iinteʹmes iinn alggmeerai musikkfeʹsttvaal veäʹǩǩpuuʹtʼteei tuâi. Tuâi oʹnnstemvuõđlaž håiddmõõžž oouʹdad ââʹnteei škoouʹlʼjumuš, sääʹmǩiõlsilttõs di riʹjttjeei eŋgglõsǩiõl silttõs. Projeʹktt-tuâjjla päʹlǩǩmõš meäʹrrjââvv Lääʹddjânnam sääʹmteeʹǧǧ päʹlǩǩriâšldõõǥǥ väʹǯǯelvuõtttääʹzz VII/I mieʹldd (vuâđđpäʹlǩǩ lij 1 755,62 euʹrred/mp). Vuâđđpääʹlǩ lââʹssen määuʹset 24 %:t sääʹmvuuʹd lââʹss da tuâjjtobddmõõžž mieʹldd meäʹrrjâʹvve tuâjjtobddâmlääʹzz. Projeʹktt-tuâjjla tuåimmpäiʹǩǩ lij sääʹmkulttuurkõõskõõzz Sajoozzâst.</p>
<p>Ooccmõõžž mieʹlddõõzzineez âʹlǧǧe vuõltteed sääʹmteeʹǧǧ tuâjjlažkådda 11.5.2018 čiâss 16.00 mõõneeʹst addrõʹsse Sajos, 99870 Aanar. Lââʹssteâđaid tuâjast oudd sääʹm-musikk-kõõskõõzz plaaneei Oula Guttorm teʹl. 050 574 2765, oula.guttorm(at)samediggi.fi. Sääʹmteeʹǧǧ tuåimmjumuʹšše vuäitt tobdstõõttâd neʹttaddrõõzzâst www.samediggi.fi da Iinteʹmes iinn-alggmeerai musikkpoʹdde addrõõzzâst: www.ijahisidja.fi .</p>
<p>Aanrest 17.4.2018 Sääʹmteʹǧǧ</p>
</body></document>
