<document xml:lang="sms" id="no_id">
  <header>
    <title>Samediggi - Saamelaiskäräjät - Sajoozz vä´lddkue´rnec &amp;#269;uä´jtemkrii´lc</title>
    <genre code="admin"/>
    <author>
      <unknown/>
    </author>
    <translator>
      <unknown/>
    </translator>
    <translated_from xml:lang="fin"/>
    <wordcount>26</wordcount>
    <conversion_status type="standard"/>
    <availability>
      <free/>
    </availability>
    <submitter name="Børre Gaup" email="albbas@gmail.com"/>
    <multilingual>
      <language xml:lang="fin"/>
    </multilingual>
    <origFileName>http://www.samediggi.fi/index2.php?option=com_content&amp;task=view&amp;id=505&amp;lang=nuortta.html</origFileName>
    <parallel_text xml:lang="fin" location="index2.php_option=com_content_task=view_id=505_lang=finnish.html"/>
    <parallel_text xml:lang="smn" location="index2.php_option=com_content_task=view_id=505_lang=anaras.html"/>
    <metadata>
      <uncomplete/>
    </metadata>
    <version>XSLtemplate $Revision$; file-specific xsl  Revision; common.xsl  $Revision: 154948 $; </version>
  </header>
  <body>
    <p>Sajoozz väʹlddkueʹrnec čuäʹjtemkriiʹlc</p>
    <p>Sajoozz väʹlddkueʹrnec čuäʹjtemkriiʹlc di studia pleässjemšâʹlddrääni da tõi jååʹđtemvaauni haʹŋǩǩumuužž kuõskki taʹrjjeemraukkmõš ääʹveet Hilma -iʹlmmtemkääzzkõõzzâst 18.8.2011. Taʹrjjeemǩeâstt poott 12.9.2011 čiâss 16.00.</p>
    <p>Looǥǥ Taʹrjjeemraukkmõõžž.</p>
  </body>
</document>
