<document xml:lang="sms" id="no_id"><header><title>Samediggi - Saamelaiskäräjät - Vuä´nkânji</title><genre code="admin"/><author><unknown/></author><translator><unknown/></translator><translated_from xml:lang="fin"/><wordcount>56</wordcount><conversion_status type="standard"/><availability><free/></availability><multilingual/><origFileName>http://www.samediggi.fi/index2.php?option=com_content&amp;task=view&amp;id=306&amp;lang=nuortta.html</origFileName><parallel_text xml:lang="eng" location="index2.php_option=com_content_task=view_id=306_lang=english.html"/><parallel_text xml:lang="fin" location="index2.php_option=com_content_task=view_id=306_lang=finnish.html"/><parallel_text xml:lang="sme" location="index2.php_option=com_content_task=view_id=306_lang=davvi.html"/><parallel_text xml:lang="smn" location="index2.php_option=com_content_task=view_id=306_lang=anaras.html"/><metadata><uncomplete/></metadata><version>XSLtemplate $Revision$; file-specific xsl  Revision; common.xsl  $Revision$; </version></header><body><p>Vuäʹnkânji</p>
<p>Haʹŋǩǩõõzz šorradvuõtt 4800 brm2</p>
<p xml:lang="smn">Täävtõshâʹdd (alv 0) 12 milj. €</p>
<p><em type="italic">Tuåimmjumuužž </em></p>
<p type="listitem">vaaldšem tuåimmjumuužž</p>
<p type="listitem">kulttuurtuåimmjumuužž</p>
<p type="listitem">mättʼtõs- da tuʹtǩǩeemtuåimmjumuš</p>
<p type="listitem">jieʹllemvueʹjji ooudâsviikkâmtuåimmjumuužž</p>
<p type="listitem">tueʹrjjeemkääzzkõõzz</p>
<p><em type="italic">Siiskâž </em></p>
<p type="listitem">sääʹm vaaldšem-, kulttuur, škoouʹlʼjumuš- da siltteemkõskkeem</p>
<p type="listitem">poddpõrtt (jieʹllikartt, musiikk, såbbar da konfereens)</p>
<p type="listitem">saaʹmi parlamenttpõrtt Lääʹddjânnmest</p>
<p type="listitem">jeeʹres vuäʹsstuåimmjumuužž õõutsââʹjest räʹjje tuåimjeeʹes da čââpp obbvuõđ</p>
<p><em type="italic">Äiʹǧǧtaull </em></p>
<p>2008 arkktehtǩeâštõõttmõš</p>
<p>2009 alggveârlaž plaan</p>
<p>2010–2011 raajjmõš</p>
<p>2012 kulttuurkõõskõs tuåimmjemen</p>
</body></document>
